watex/__init__.py
watex/_distributor_init.py
watex/_docstring.py
watex/_isotonic.pyx
watex/_typing.py
watex/_version.py
watex/_watexlog.py
watex/base.py
watex/cli.py
watex/decorators.py
watex/edi.py
watex/exceptions.py
watex/metrics.py
watex/property.py
watex/site.py
watex/transformers.py
watex/wlog.yml
watex/_build/__init__.py
watex/_build/_check_build.pyx
watex/analysis/__init__.py
watex/analysis/decomposition.py
watex/analysis/dimensionality.py
watex/analysis/factor.py
watex/cases/__init__.py
watex/cases/features.py
watex/cases/modeling.py
watex/cases/prepare.py
watex/cases/processing.py
watex/datasets/__init__.py
watex/datasets/_config.py
watex/datasets/_hongliu.py
watex/datasets/_p.py
watex/datasets/dload.py
watex/datasets/gdata.py
watex/datasets/io.py
watex/datasets/rload.py
watex/datasets/sets.py
watex/datasets/setup.py
watex/datasets/data/__init__.py
watex/datasets/data/b.pkl
watex/datasets/data/bagoue.csv
watex/datasets/data/boston_house_prices.csv
watex/datasets/data/boundiali_ves.csv
watex/datasets/data/dcerp_gbalo.csv
watex/datasets/data/dcves_gbalo.csv
watex/datasets/data/e.h5
watex/datasets/data/iris.csv
watex/datasets/data/mxs.joblib
watex/datasets/data/nlogs+.csv
watex/datasets/data/nlogs.csv
watex/datasets/data/semien_ves.csv
watex/datasets/data/tankesse.csv
watex/datasets/data/wine_data.csv
watex/datasets/data/edis/__init__.py
watex/datasets/data/edis/raw.E.zip
watex/datasets/data/edis/s.E.zip
watex/datasets/descr/__init__.py
watex/datasets/descr/bagoue.rst
watex/datasets/descr/boston_house_prices.rst
watex/datasets/descr/boundiali_ves.rst
watex/datasets/descr/california_housing.rst
watex/datasets/descr/gbalo_erp.rst
watex/datasets/descr/gbalo_ves.rst
watex/datasets/descr/huayuan_edis.rst
watex/datasets/descr/iris.rst
watex/datasets/descr/nanshang++.rst
watex/datasets/descr/nanshang+.rst
watex/datasets/descr/nanshang.rst
watex/datasets/descr/wine_data.rst
watex/etc/AGSO.csv
watex/etc/AGSO_STCODES.csv
watex/etc/__XTyT.pkl
watex/etc/__Xy.pkl
watex-0.3.3.dist-info/LICENSE
watex-0.3.3.dist-info/METADATA
watex-0.3.3.dist-info/WHEEL
watex-0.3.3.dist-info/entry_points.txt
watex-0.3.3.dist-info/top_level.txt
watex-0.3.3.dist-info/zip-safe
watex-0.3.3.dist-info/RECORD
