Metadata-Version: 2.1
Name: watex
Version: 0.3.3
Summary: Machine learning research in water exploration
Home-page: https://github.com/WEgeophysics/watex
Download-URL: https://pypi.org/project/watex/#files
Author: Laurent Kouadio
Author-email: Laurent Kouadio <etanoyau@gmail.com>
Maintainer: Laurent Kouadio
Maintainer-email: etanoyau@gmail.com
License: BSD 3-Clause License
Project-URL: Home, https://watex.readthedocs.io
Project-URL: Documentation, https://watex.readthedocs.io/en/latest/api_references.html
Project-URL: Bugs Tracker, https://github.com/WEgeophysics/watex/issues
Project-URL: Installation Guide, https://watex.readthedocs.io/en/latest/installation.html
Project-URL: User Guide, https://watex.readthedocs.io/en/latest/user_guide.html
Project-URL: Source, https://github.com/WEgeophysics/watex
Project-URL: Download, https://pypi.org/project/watex/#files
Keywords: exploration,groundwater,machine learning,water,hydro-geophysics
Classifier: Development Status :: 3 - Alpha
Classifier: Intended Audience :: Science/Research
Classifier: Intended Audience :: Developers
Classifier: Topic :: Software Development
Classifier: Topic :: Scientific/Engineering
Classifier: Programming Language :: C
Classifier: Programming Language :: Python
Classifier: Programming Language :: Python :: 3.9
Classifier: Programming Language :: Python :: 3.10
Classifier: Programming Language :: Python :: 3.11
Classifier: Programming Language :: Python :: Implementation :: CPython
Classifier: Operating System :: OS Independent
Classifier: Operating System :: Microsoft :: Windows
Classifier: Operating System :: POSIX
Classifier: Operating System :: Unix
Requires-Python: >=3.9
License-File: LICENSE
Requires-Dist: seaborn >=0.12.0
Requires-Dist: pandas >=1.4.0
Requires-Dist: Cython >=0.29.33
Requires-Dist: PyYAML >=5.0.0
Requires-Dist: openpyxl >=3.0.3
Requires-Dist: pyproj >=3.3.0
Requires-Dist: pycsamt >=1.1.2
Requires-Dist: tqdm >=4.64.1
Requires-Dist: tables >=3.6.0
Requires-Dist: scikit-learn ==1.2.1
Requires-Dist: joblib >=1.2.0
Requires-Dist: threadpoolctl >=3.1.0
Requires-Dist: matplotlib ==3.5.3
Requires-Dist: statsmodels >=0.13.1
Requires-Dist: numpy >=1.23.0
Requires-Dist: scipy >=1.9.0
Requires-Dist: h5py >=3.2.0
Requires-Dist: pytest
Provides-Extra: dev
Requires-Dist: click ; extra == 'dev'
Requires-Dist: missingno >=0.4.2 ; extra == 'dev'
Requires-Dist: yellowbrick >=1.5.0 ; extra == 'dev'
Requires-Dist: pyjanitor >=0.1.7 ; extra == 'dev'
Requires-Dist: mlxtend >=0.21 ; extra == 'dev'
Requires-Dist: xgboost >=1.7.0 ; extra == 'dev'
